Workbook

Sheet Cluster Summary
A1: No. | B1: Main Topic | C1: Cluster Name | D1: Pillar Topic | E1: Total Topics
A2: 1 | B2: Sofas, Seating & Living Room Furniture | C2: Black Sofa Ideas | D2: how to decorate my living room with black sofas | E2: =COUNTIF('All Keywords by Cluster'!$C$2:$C$4288,$C2) -> 9
A3: 2 | B3: Sofas, Seating & Living Room Furniture | C3: Brown Sofa Ideas | D3: how to decorate your living room with brown sofa | E3: =COUNTIF('All Keywords by Cluster'!$C$2:$C$4288,$C3) -> 8
A4: 3 | B4: Sofas, Seating & Living Room Furniture | C4: Chair Reupholstery | D4: how to reupholster a living room chair | E4: =COUNTIF('All Keywords by Cluster'!$C$2:$C$4288,$C4) -> 21
A5: 4 | B5: Sofas, Seating & Living Room Furniture | C5: Chair Sizing | D5: what do you call a living room chair | E5: =COUNTIF('All Keywords by Cluster'!$C$2:$C$4288,$C5) -> 24
A6: 5 | B6: Sofas, Seating & Living Room Furniture | C6: Coffee Table Decor | D6: should a living room have a coffee table | E6: =COUNTIF('All Keywords by Cluster'!$C$2:$C$4288,$C6) -> 23
A7: 6 | B7: Sofas, Seating & Living Room Furniture | C7: Console Tables | D7: where to put console table in living room | E7: =COUNTIF('All Keywords by Cluster'!$C$2:$C$4288,$C7) -> 19
A8: 7 | B8: Sofas, Seating & Living Room Furniture | C8: Decor Furniture Accessories | D8: decor accents | E8: =COUNTIF('All Keywords by Cluster'!$C$2:$C$4288,$C8) -> 21
A9: 8 | B9: Sofas, Seating & Living Room Furniture | C9: End Table Styling | D9: where to put end tables in living room | E9: =COUNTIF('All Keywords by Cluster'!$C$2:$C$4288,$C9) -> 24
A10: 9 | B10: Sofas, Seating & Living Room Furniture | C10: Furniture Decor | D10: furniture home decoration | E10: =COUNTIF('All Keywords by Cluster'!$C$2:$C$4288,$C10) -> 12
A11: 10 | B11: Sofas, Seating & Living Room Furniture | C11: Furniture Decor Stores | D11: furniture decor | E11: =COUNTIF('All Keywords by Cluster'!$C$2:$C$4288,$C11) -> 13
A12: 11 | B12: Sofas, Seating & Living Room Furniture | C12: Furniture Home Accessories | D12: furniture home decor | E12: =COUNTIF('All Keywords by Cluster'!$C$2:$C$4288,$C12) -> 25
A13: 12 | B13: Sofas, Seating & Living Room Furniture | C13: Furniture Store Decor | D13: furniture store by me | E13: =COUNTIF('All Keywords by Cluster'!$C$2:$C$4288,$C13) -> 17
... A252: 251 | B252: Storage, Cleaning & DIY Projects | C252: TV Wire Concealment | D252: how to hide tv cables and wires | E252: =COUNTIF('All Keywords by Cluster'!$C$2:$C$4288,$C252) -> 5

Sheet Main Topics
A1: No. | B1: Main Topic | C1: Total Clusters | D1: Total Keywords | E1: What It Covers
A2: 1 | B2: Sofas, Seating & Living Room Furniture | C2: =COUNTIF('Cluster Summary'!$B$2:$B$252,$B2) -> 41 | D2: =COUNTIF('All Keywords by Cluster'!$B$2:$B$4288,$B2) -> 713 | E2: Sofas, chairs, recliners, ottomans, coffee, end, side and console tables, TV stands, and general furniture and furniture-store topics.
A3: 2 | B3: Bedroom & Bathroom Decor | C3: =COUNTIF('Cluster Summary'!$B$2:$B$252,$B3) -> 28 | D3: =COUNTIF('All Keywords by Cluster'!$B$2:$B$4288,$B3) -> 509 | E3: Beds, headboards, bedding, dressers, nightstands and bedroom styling; bathroom vanities, sinks and faucets.
A4: 3 | B4: Dining, Kitchen & Home Office | C4: =COUNTIF('Cluster Summary'!$B$2:$B$252,$B4) -> 14 | D4: =COUNTIF('All Keywords by Cluster'!$B$2:$B$4288,$B4) -> 214 | E4: Dining tables and centerpieces, kitchen decor and cabinets, wine glasses, home office desks, chairs and office decor.
A5: 4 | B5: Lighting & Smart Home | C5: =COUNTIF('Cluster Summary'!$B$2:$B$252,$B5) -> 21 | D5: =COUNTIF('All Keywords by Cluster'!$B$2:$B$4288,$B5) -> 366 | E5: Lamps, chandeliers, ceiling and bathroom lighting, light bulbs, LED ideas, and smart bulb setup and compatibility.
A6: 5 | B6: Wall Decor, Mirrors & Frames | C6: =COUNTIF('Cluster Summary'!$B$2:$B$252,$B6) -> 40 | D6: =COUNTIF('All Keywords by Cluster'!$B$2:$B$4288,$B6) -> 713 | E6: Wall art, murals, wall painting techniques, canvas and tapestries, mirrors (placement, install, cleaning), picture and wall frames.
A7: 6 | B7: Rugs, Flooring & Window Treatments | C7: =COUNTIF('Cluster Summary'!$B$2:$B$252,$B7) -> 28 | D7: =COUNTIF('All Keywords by Cluster'!$B$2:$B$4288,$B7) -> 505 | E7: Area, bath, outdoor and non-slip rugs, tile and vinyl flooring and retailers, curtains, shades and curtain rods.
A8: 7 | B8: Home Accessories, Textiles & Plants | C8: =COUNTIF('Cluster Summary'!$B$2:$B$252,$B8) -> 32 | D8: =COUNTIF('All Keywords by Cluster'!$B$2:$B$4288,$B8) -> 549 | E8: Decorative accessories, candles, fragrance, ornaments, pillows, throws, cushions, slipcovers, vases, planters and indoor plants.
A9: 8 | B9: Seasonal, Holiday & Outdoor Decor | C9: =COUNTIF('Cluster Summary'!$B$2:$B$252,$B9) -> 22 | D9: =COUNTIF('All Keywords by Cluster'!$B$2:$B$4288,$B9) -> 315 | E9: Christmas, Halloween, Fall, Thanksgiving, Easter and winter decor, holiday crafts, and patio decor.
A10: 9 | B10: Storage, Cleaning & DIY Projects | C10: =COUNTIF('Cluster Summary'!$B$2:$B$252,$B10) -> 25 | D10: =COUNTIF('All Keywords by Cluster'!$B$2:$B$4288,$B10) -> 403 | E10: Shelves, cabinets and wardrobes, storage benches, wire concealment, home decor cleaning, and clay and craft DIY projects.
B11: Total | C11: =SUM(C2:C10) -> 251 | D11: =SUM(D2:D10) -> 4287

Sheet All Keywords by Cluster
A1: No. | B1: Main Topic | C1: Cluster Name | D1: Topic Type | E1: Keyword / Topic | F1: Post URL
A2: 1 | B2: Sofas, Seating & Living Room Furniture | C2: Black Sofa Ideas | D2: Pillar Topic | E2: how to decorate my living room with black sofas | F2: https://homelyfusion.com/how-to-decorate-my-living-room-with-black-sofas/
A3: 2 | B3: Sofas, Seating & Living Room Furniture | C3: Black Sofa Ideas | D3: Sub-topic | E3: how to decorate a living room with black sofas | F3: https://homelyfusion.com/how-to-decorate-a-living-room-with-black-sofas/
A4: 3 | B4: Sofas, Seating & Living Room Furniture | C4: Black Sofa Ideas | D4: Sub-topic | E4: how to decorate a living room with cream sofas | F4: https://homelyfusion.com/how-to-decorate-a-living-room-with-cream-sofas/
A5: 4 | B5: Sofas, Seating & Living Room Furniture | C5: Black Sofa Ideas | D5: Sub-topic | E5: how to decorate a living room with dark blue sofas | F5: https://homelyfusion.com/how-to-decorate-a-living-room-with-dark-blue-sofas/
A6: 5 | B6: Sofas, Seating & Living Room Furniture | C6: Black Sofa Ideas | D6: Sub-topic | E6: how to decorate a living room with green sofas | F6: https://homelyfusion.com/how-to-decorate-a-living-room-with-green-sofas/
A7: 6 | B7: Sofas, Seating & Living Room Furniture | C7: Black Sofa Ideas | D7: Sub-topic | E7: how to decorate a living room with purple sofas | F7: https://homelyfusion.com/how-to-decorate-a-living-room-with-purple-sofas/
A8: 7 | B8: Sofas, Seating & Living Room Furniture | C8: Black Sofa Ideas | D8: Sub-topic | E8: how to decorate a living room with red sofas | F8: https://homelyfusion.com/how-to-decorate-a-living-room-with-red-sofas/
A9: 8 | B9: Sofas, Seating & Living Room Furniture | C9: Black Sofa Ideas | D9: Sub-topic | E9: how to decorate living room with dark chocolate leather sofas | F9: https://homelyfusion.com/how-to-decorate-living-room-with-dark-chocolate-leather-sofas/
A10: 9 | B10: Sofas, Seating & Living Room Furniture | C10: Black Sofa Ideas | D10: Sub-topic | E10: how to decorate living room with olive velvet sofas | F10: https://homelyfusion.com/how-to-decorate-living-room-with-olive-velvet-sofas/
A11: 10 | B11: Sofas, Seating & Living Room Furniture | C11: Brown Sofa Ideas | D11: Pillar Topic | E11: how to decorate your living room with brown sofa | F11: https://homelyfusion.com/how-to-decorate-your-living-room-with-brown-sofa/
A12: 11 | B12: Sofas, Seating & Living Room Furniture | C12: Brown Sofa Ideas | D12: Sub-topic | E12: how decorate a living room with brown sofa | F12: https://homelyfusion.com/how-decorate-a-living-room-with-brown-sofa/
A13: 12 | B13: Sofas, Seating & Living Room Furniture | C13: Brown Sofa Ideas | D13: Sub-topic | E13: how to decorate a brown couch | F13: https://homelyfusion.com/how-to-decorate-a-brown-couch/
... A4288: 4287 | B4288: Storage, Cleaning & DIY Projects | C4288: TV Wire Concealment | D4288: Sub-topic | E4288: how to hide tv wires | F4288: https://homelyfusion.com/how-to-hide-tv-wires/

Sheet Removed Keywords
A1: No. | B1: Keyword | C1: Post URL | D1: Removal Reason | E1: Kept Instead (Duplicate Of)
A2: 1 | B2: can ikea bedroom beds fit in car | C2: https://homelyfusion.com/can-ikea-bedroom-beds-fit-in-car/ | D2: Duplicate keyword (same search intent) | E2: can ikea bedroom beds fit in car
A3: 2 | B3: a chair in the living room | C3: https://homelyfusion.com/a-chair-in-the-living-room/ | D3: Near-duplicate (cannibalizes another keyword) | E3: a chair in a living room
A4: 3 | B4: at home accessories store | C4: https://homelyfusion.com/at-home-accessories-store/ | D4: Near-duplicate (cannibalizes another keyword) | E4: home accessories store
A5: 4 | B5: best blinds for a bedroom top cordless and blackout window shades | C5: https://homelyfusion.com/best-blinds-for-a-bedroom-top-cordless-and-blackout-window-shades/ | D5: Near-duplicate (cannibalizes another keyword) | E5: best blinds for bedroom top cordless and blackout window shades
A6: 5 | B6: best floor lamp for reading top adjustable led lamps with eye care features | C6: https://homelyfusion.com/best-floor-lamp-for-reading-top-adjustable-led-lamps-with-eye-care-features/ | D6: Near-duplicate (cannibalizes another keyword) | E6: best floor lamps for reading top adjustable led lamps with eye care features
A7: 6 | B7: best rugs for a kitchen top cushioned non slip and washable mats | C7: https://homelyfusion.com/best-rugs-for-a-kitchen-top-cushioned-non-slip-and-washable-mats/ | D7: Near-duplicate (cannibalizes another keyword) | E7: best rugs for kitchen top cushioned non slip and washable mats
A8: 7 | B8: calvin heights sectional sofa | C8: https://homelyfusion.com/calvin-heights-sectional-sofa/ | D8: Near-duplicate (cannibalizes another keyword) | E8: calvin heights sectional
A9: 8 | B9: can i put my china cabinet in living room | C9: https://homelyfusion.com/can-i-put-my-china-cabinet-in-living-room/ | D9: Near-duplicate (cannibalizes another keyword) | E9: can i put my china cabinet in the living room
A10: 9 | B10: can you fire clay in home oven | C10: https://homelyfusion.com/can-you-fire-clay-in-home-oven/ | D10: Near-duplicate (cannibalizes another keyword) | E10: can you fire clay in a home oven
A11: 10 | B11: can you put a china cabinet in the living room | C11: https://homelyfusion.com/can-you-put-a-china-cabinet-in-the-living-room/ | D11: Near-duplicate (cannibalizes another keyword) | E11: can you put a china cabinet in a living room
A12: 11 | B12: can you put china cabinet in living room | C12: https://homelyfusion.com/can-you-put-china-cabinet-in-living-room/ | D12: Near-duplicate (cannibalizes another keyword) | E12: can you put a china cabinet in a living room
A13: 12 | B13: decorative accessories for home | C13: https://homelyfusion.com/decorative-accessories-for-home/ | D13: Near-duplicate (cannibalizes another keyword) | E13: decorative accessories for the home
... A169: 168 | B169: where to put table lamps in living room | C169: https://homelyfusion.com/where-to-put-table-lamps-in-living-room/ | D169: Near-duplicate (cannibalizes another keyword) | E169: how to place table lamps in living room
A170: 169 | B170: a honeywell home thermostat | C170: https://homelyfusion.com/a-honeywell-home-thermostat/ | D170: Off-niche: HVAC, electrical or unrelated home-technology query
A171: 170 | B171: ac fans for home | C171: https://homelyfusion.com/ac-fans-for-home/ | D171: Off-niche: HVAC, electrical or unrelated home-technology query
A172: 171 | B172: ac vents for home | C172: https://homelyfusion.com/ac-vents-for-home/ | D172: Off-niche: HVAC, electrical or unrelated home-technology query
A173: 172 | B173: are ac units covered under home insurance | C173: https://homelyfusion.com/are-ac-units-covered-under-home-insurance/ | D173: Off-niche: HVAC, electrical or unrelated home-technology query
A174: 173 | B174: are ac units covered under home warranty | C174: https://homelyfusion.com/are-ac-units-covered-under-home-warranty/ | D174: Off-niche: HVAC, electrical or unrelated home-technology query
A175: 174 | B175: are home appliances ac or dc | C175: https://homelyfusion.com/are-home-appliances-ac-or-dc/ | D175: Off-niche: HVAC, electrical or unrelated home-technology query
A176: 175 | B176: are home chargers ac or dc | C176: https://homelyfusion.com/are-home-chargers-ac-or-dc/ | D176: Off-niche: HVAC, electrical or unrelated home-technology query
A177: 176 | B177: are home ev chargers ac or dc | C177: https://homelyfusion.com/are-home-ev-chargers-ac-or-dc/ | D177: Off-niche: HVAC, electrical or unrelated home-technology query
A178: 177 | B178: are home heating oil prices coming down | C178: https://homelyfusion.com/are-home-heating-oil-prices-coming-down/ | D178: Off-niche: HVAC, electrical or unrelated home-technology query
A179: 178 | B179: are home heating oil prices dropping | C179: https://homelyfusion.com/are-home-heating-oil-prices-dropping/ | D179: Off-niche: HVAC, electrical or unrelated home-technology query
A180: 179 | B180: are home heating oil prices expected to go down | C180: https://homelyfusion.com/are-home-heating-oil-prices-expected-to-go-down/ | D180: Off-niche: HVAC, electrical or unrelated home-technology query
A181: 180 | B181: are home heating oil prices expected to rise | C181: https://homelyfusion.com/are-home-heating-oil-prices-expected-to-rise/ | D181: Off-niche: HVAC, electrical or unrelated home-technology query
... A942: 941 | B942: how to use google home with spotify | C942: https://homelyfusion.com/how-to-use-google-home-with-spotify/ | D942: Off-niche: unrelated smart-speaker/home-technology query

Sheet Read Me
A1: Read Me
A2: Label | B2: Detail
A3: Title | B3: HomelyFusion Home Decor Keyword Cleaning, De-duplication & Re-clustering
A4: Source | B4: Original workbook: homelyfusion keywords.xlsx; sheet: Posts; columns used: Ser, Post URL, Keyword. The Posts sheet was the only source used.
A5: Total keywords received | B5: 5228
A6: Keywords removed | B6: 941
A7: Keywords kept | B7: 4287
A8: Total clusters | B8: 251
A9: Cluster size guideline | B9: Target 8–25 keywords per cluster; no cluster exceeds 25.
A10: Clusters below 8 keywords | B10: 6. Christmas Stockings (3): Only three retained stocking keywords; merging would blur the specific holiday product intent. Decorative Bookends (4): Only four retained bookend keywords; the product intent is narrow. Plants & Greenery (6): Only six retained broad plant/greenery keywords; merging would blur plant-focused intent. TV Wire Concealment (5): Only five retained wire-concealment keywords; they share a distinct home-aesthetic problem. Thanksgiving Decor (7): Only seven retained Thanksgiving-specific keywords; merging would blur holiday intent. Wine Glasses (2): Only two retained wine-glass keywords; merging would blur the specific tableware intent.
A11: Average cluster size | B11: 17.08 keywords
A12: Maximum cluster size | B12: Wool Rug Cleaning
A13: Cluster naming rules | B13: Unique, natural 2–5 word Title Case names; no category prefixes and no hyphen separators. Names describe the cluster topic rather than mechanically repeating the pillar wording.
... A24: Main topic consolidation | B24: Main topics were regrouped by the primary subject of each cluster: (1) sofas, seating and living room furniture, (2) bedroom and bathroom decor, (3) dining, kitchen and home office, (4) lighting and smart home, (5) wall decor, mirrors and frames, (6) rugs, flooring and window treatments, (7) home accessories, textiles and plants, (8) seasonal, holiday and outdoor decor, (9) storage, cleaning and DIY projects. The former catch-all "General Home Decor" group was split across these by subject, and product clusters that carried a room name (for example bedroom mirrors or bathroom lighting) were placed with their product type. Cluster names, pillar topics, keywords and Post URLs were not changed; only the Main Topic assignment, sort order and row numbers (No.) were updated.
